{"id":10611,"title":"Водовзводная башня Московского Кремля","slug":"vodovzvodnaya-bashnya-sviblova","address":"наб. Кремлёвская","timetable":"","phone":"","is_stub":false,"body_text":"<p>Водовзводная или Свиблова башня — это юго-западная угловая башня Московского Кремля, она находится на углу Кремлёвской набережной и Александровского сада. Построена в 1488 году Антоном Фрязиным. Второе её название — Свиблова — от боярского рода Свибло, чей двор находился рядом.</p>\n<p>Своё современное название башня получила в 1633 году. В ней установили машину для подачи воды из Москвы-реки в Кремль. Это был первый в Москве водопровод, по свинцовым трубам которого вода подавалась в сады, а также в Сытный и Кормовой дворец.</p>\n<p>На Москве-реке у башни был портомойный плот, где полоскали бельё, здесь же были принадлежности для этого занятия, а выстиранное в реке бельё носили обратно в Кремль.</p>\n<p>В 1805 году из-за ветхости её пришлось разобрать и построить заново. Но недолго она радовала взгляд москвичей: в 1812 году отступающая армия Наполеона взорвала башню. В 1819 году её снова восстановили, но без бойниц, а слуховые окна украсили тосканскими портиками.</p>\n<p>В 1937 году над башней засверкала рубиновая звезда. Размах её лучей составляет три метра. При этом это самая маленькая звезда среди всех Кремлёвских.</p>\n<p>После распада Советского Союза, изображение Водовзводной башни поместили на внутреннюю сторону обложки паспорта гражданина Российской Федерации.</p>\n","description":"<p>Башня, через которую подавали воду в Кремль и на которой установлена самая маленькая из кремлёвских звёзд.</p>\n","site_url":"https://kudago.com/msk/place/vodovzvodnaya-bashnya-sviblova/","foreign_url":"http://www.kreml.ru/ru/kremlin/towers/Vodovzvodnaya/","coords":{"lat":55.74816605968328,"lon":37.61368989421396},"subway":"Александровский сад, Боровицкая","favorites_count":6,"images":[{"image":"https://kudago.com/media/images/place/d9/d8/d9d874dbe90c2a6975decb39eedb4d51.jpg","thumbnails":{"640x384":"https://kudago.com/media/thumbs/640x384/images/place/d9/d8/d9d874dbe90c2a6975decb39eedb4d51.jpg","144x96":"https://kudago.com/media/thumbs/144x96/images/place/d9/d8/d9d874dbe90c2a6975decb39eedb4d51.jpg"},"source":{"name":"commons.wikimedia.org","link":"https://commons.wikimedia.org/wiki/Category:Vodovzvodnaya_Tower#/media/File:%D0%9A%D1%80%D0%B5%D0%BC%D0%BB%D0%B5%D0%B2%D1%81%D0%BA%D0%B0%D1%8F_%D0%91%D0%B0%D1%88%D0%BD%D1%8F_3.jpg"}},{"image":"https://kudago.com/media/images/place/14/fa/14fa1d9d1d6eff518e77f4de3c565080.jpg","thumbnails":{"640x384":"https://kudago.com/media/thumbs/640x384/images/place/14/fa/14fa1d9d1d6eff518e77f4de3c565080.jpg","144x96":"https://kudago.com/media/thumbs/144x96/images/place/14/fa/14fa1d9d1d6eff518e77f4de3c565080.jpg"},"source":{"name":"yaroslavglukhov.tourister.ru","link":"https://yaroslavglukhov.tourister.ru/photoalbum/22442"}},{"image":"https://kudago.com/media/images/place/77/91/7791d3e9e484882699dfd0d786ff9fee.jpg","thumbnails":{"640x384":"https://kudago.com/media/thumbs/640x384/images/place/77/91/7791d3e9e484882699dfd0d786ff9fee.jpg","144x96":"https://kudago.com/media/thumbs/144x96/images/place/77/91/7791d3e9e484882699dfd0d786ff9fee.jpg"},"source":{"name":"wikimedia.org","link":"https://commons.wikimedia.org/wiki/File:Kremlin_towers_Vodovzvodnaya_night.jpg"}}],"comments_count":0,"is_closed":false,"categories":["attractions","sights"],"short_title":"Водовзводная башня","tags":["кремль","достопримечательности","замки, дворцы","интересные места"],"location":"msk","age_restriction":null,"disable_comments":false,"has_parking_lot":false}