{"id":16980,"title":"Кировоградские пруды","slug":"kirovogradskie-prudy","address":"Кировоградская, 36","timetable":"ежедневно весь день","phone":"","is_stub":false,"body_text":"<p>Все три пруда образованы в русле реки Городни. Когда-то был и четвертый водоем, но его засыпали несколько десятилетий назад. Пруды носят общее название - Кировоградские, так же называется и парк на побережье. Отдыхают здесь в основном местные жители - пока на этой территории нет богатого выбора развлечений, но для тихой вечерней прогулки всей семьей она подходит как нельзя лучше. Летом на побережье можно загорать, правда, купаться ни в одном из прудов нельзя - вода в них довольно грязная.</p>\n","description":"<p>Вокруг трех прудов на Кировоградской улице разбит небольшой парк.</p>\n","site_url":"https://kudago.com/msk/place/kirovogradskie-prudy/","foreign_url":"","coords":{"lat":55.60526838481078,"lon":37.59721593254174},"subway":"Пражская","favorites_count":11,"images":[{"image":"https://kudago.com/media/images/place/5c/8e/5c8e2c3d0380716bb7440bb602512e83.jpg","thumbnails":{"640x384":"https://kudago.com/media/thumbs/640x384/images/place/5c/8e/5c8e2c3d0380716bb7440bb602512e83.jpg","144x96":"https://kudago.com/media/thumbs/144x96/images/place/5c/8e/5c8e2c3d0380716bb7440bb602512e83.jpg"},"source":{"name":"relax-in-moscow.ru","link":"http://relax-in-moscow.ru/vodoemi/kirovogradskiy-prudi"}}],"comments_count":2,"is_closed":false,"categories":["park","attractions"],"short_title":"Кировоградские пруды","tags":["всей семьей","парки (интересные места, отдых)","парки","прогулка","достопримечательности"],"location":"msk","age_restriction":null,"disable_comments":false,"has_parking_lot":false}