{"id":25518,"title":"граффити «Урангео»","slug":"graffiti-urangeo","address":"ул. Малая Ордынка, 38, стр 1","timetable":"","phone":"","is_stub":false,"body_text":"<p>Автор этого граффити — российский художник Тихон Пенкин. Его название, кстати, не просто метафора или игра слов, «Урангео» — геологическая компания, расположенная по соседству. А картина воплощает те образы, что рождает это одновременно странное и красивое слово.</p>\n<p>Граффити появилось в рамках фестиваля стрит–арта «Мост».</p>\n","description":"<p>Сюрреалистичное изображение можно найти на стене дома неподалеку от театра Луны.</p>\n","site_url":"https://kudago.com/msk/place/graffiti-urangeo/","foreign_url":"","coords":{"lat":55.73345699999998,"lon":37.62536099999998},"subway":"Добрынинская, Полянка","favorites_count":8,"images":[{"image":"https://kudago.com/media/images/place/34/fb/34fbad85c091e1adc8ff1db673b0bab2.jpg","thumbnails":{"640x384":"https://kudago.com/media/thumbs/640x384/images/place/34/fb/34fbad85c091e1adc8ff1db673b0bab2.jpg","144x96":"https://kudago.com/media/thumbs/144x96/images/place/34/fb/34fbad85c091e1adc8ff1db673b0bab2.jpg"},"source":{"name":"leonovvaleri.livejournal.com","link":"http://leonovvaleri.livejournal.com/57387.html"}},{"image":"https://kudago.com/media/images/place/6e/0a/6e0aeaf7c0c8bad5d7651ec427974536.jpg","thumbnails":{"640x384":"https://kudago.com/media/thumbs/640x384/images/place/6e/0a/6e0aeaf7c0c8bad5d7651ec427974536.jpg","144x96":"https://kudago.com/media/thumbs/144x96/images/place/6e/0a/6e0aeaf7c0c8bad5d7651ec427974536.jpg"},"source":{"name":"localway.ru","link":"https://localway.ru/moscow/guide/44"}}],"comments_count":0,"is_closed":false,"categories":["attractions","sights"],"short_title":"","tags":["граффити","интересные места","стрит-арт","достопримечательности"],"location":"msk","age_restriction":null,"disable_comments":false,"has_parking_lot":false}